errplane
