Metadata-Version: 1.0
Name: errplane
Version: 0.1.5
Summary: Python library for use with Errplane (https://errplane.com)
Home-page: http://github.com/errplane/errplane-python
Author: Todd Persen
Author-email: todd@errplane.com
License: LICENSE.txt
Platform: UNKNOWN
